semaver/__init__.py
semaver/_api.py
semaver/_error.py
semaver/_version.py
semaver/_version_range.py
semaver-0.2.1.dist-info/LICENSE.md
semaver-0.2.1.dist-info/METADATA
semaver-0.2.1.dist-info/WHEEL
semaver-0.2.1.dist-info/top_level.txt
semaver-0.2.1.dist-info/RECORD
