Metadata-Version: 2.1
Name: semaver
Version: 0.2.1
Summary: Semantic Versioning Helper for Python
Home-page: https://github.com/ashep/semaver
Author: Oleksandr Shepetko
Author-email: a@shepetko.com
License: UNKNOWN
Download-URL: https://github.com/ashep/semaver/archive/master.zip
Platform: UNKNOWN
Classifier: Development Status :: 4 - Beta
Classifier: Environment :: Console
Classifier: Environment :: Web Environment
Classifier: Intended Audience :: Developers
Classifier: License :: OSI Approved :: MIT License
Classifier: Operating System :: OS Independent
Classifier: Programming Language :: Python :: 3.6
Classifier: Programming Language :: Python :: 3.7
Classifier: Programming Language :: Python :: 3.8
Classifier: Topic :: Software Development :: Libraries :: Python Modules
